cli_fragments/__init__.py
cli_fragments/cli_fragments.py
cli_fragments-1.2.0.dist-info/LICENSE
cli_fragments-1.2.0.dist-info/METADATA
cli_fragments-1.2.0.dist-info/WHEEL
cli_fragments-1.2.0.dist-info/top_level.txt
cli_fragments-1.2.0.dist-info/RECORD
